{
  "Models": {
    "2": {
      "Position": {
        "0": "0, 0.286214, 0",
        "119": "0, 0.286214, 0"
      },
      "Rotation": {},
      "Scale": {},
      "Vector": {},
      "Vertex": {},
      "Normal": {},
      "Target": {},
      "Roll": {},
      "Angle": {},
      "Color": {},
      "Intensity": {},
      "Spot": {},
      "Point": {},
      "PositionName": "animation_00033404_mkey_2_pos_0002D204",
      "RotationName": null,
      "ScaleName": null,
      "VectorName": null,
      "VertexName": null,
      "VertexItemName": null,
      "NormalItemName": null,
      "NormalName": null,
      "TargetName": null,
      "RollName": null,
      "AngleName": null,
      "ColorName": null,
      "IntensityName": null,
      "SpotName": null,
      "PointName": null
    },
    "4": {
      "Position": {},
      "Rotation": {
        "0": "0, 0, FFFFD366",
        "119": "0, 0, FFFFD366"
      },
      "Scale": {},
      "Vector": {},
      "Vertex": {},
      "Normal": {},
      "Target": {},
      "Roll": {},
      "Angle": {},
      "Color": {},
      "Intensity": {},
      "Spot": {},
      "Point": {},
      "PositionName": null,
      "RotationName": "animation_00033404_mkey_4_rot_0002D224",
      "ScaleName": null,
      "VectorName": null,
      "VertexName": null,
      "VertexItemName": null,
      "NormalItemName": null,
      "NormalName": null,
      "TargetName": null,
      "RollName": null,
      "AngleName": null,
      "ColorName": null,
      "IntensityName": null,
      "SpotName": null,
      "PointName": null
    },
    "7": {
      "Position": {},
      "Rotation": {
        "0": "186, 6CA, FFFFEB8F",
        "119": "186, 6CA, FFFFEB8F"
      },
      "Scale": {},
      "Vector": {},
      "Vertex": {},
      "Normal": {},
      "Target": {},
      "Roll": {},
      "Angle": {},
      "Color": {},
      "Intensity": {},
      "Spot": {},
      "Point": {},
      "PositionName": null,
      "RotationName": "animation_00033404_mkey_7_rot_0002D244",
      "ScaleName": null,
      "VectorName": null,
      "VertexName": null,
      "VertexItemName": null,
      "NormalItemName": null,
      "NormalName": null,
      "TargetName": null,
      "RollName": null,
      "AngleName": null,
      "ColorName": null,
      "IntensityName": null,
      "SpotName": null,
      "PointName": null
    },
    "8": {
      "Position": {},
      "Rotation": {
        "0": "0, 0, 893",
        "119": "0, 0, 893"
      },
      "Scale": {},
      "Vector": {},
      "Vertex": {},
      "Normal": {},
      "Target": {},
      "Roll": {},
      "Angle": {},
      "Color": {},
      "Intensity": {},
      "Spot": {},
      "Point": {},
      "PositionName": null,
      "RotationName": "animation_00033404_mkey_8_rot_0002D264",
      "ScaleName": null,
      "VectorName": null,
      "VertexName": null,
      "VertexItemName": null,
      "NormalItemName": null,
      "NormalName": null,
      "TargetName": null,
      "RollName": null,
      "AngleName": null,
      "ColorName": null,
      "IntensityName": null,
      "SpotName": null,
      "PointName": null
    },
    "9": {
      "Position": {},
      "Rotation": {
        "0": "0, 0, 9E0",
        "119": "0, 0, 9E0"
      },
      "Scale": {},
      "Vector": {},
      "Vertex": {},
      "Normal": {},
      "Target": {},
      "Roll": {},
      "Angle": {},
      "Color": {},
      "Intensity": {},
      "Spot": {},
      "Point": {},
      "PositionName": null,
      "RotationName": "animation_00033404_mkey_9_rot_0002D284",
      "ScaleName": null,
      "VectorName": null,
      "VertexName": null,
      "VertexItemName": null,
      "NormalItemName": null,
      "NormalName": null,
      "TargetName": null,
      "RollName": null,
      "AngleName": null,
      "ColorName": null,
      "IntensityName": null,
      "SpotName": null,
      "PointName": null
    },
    "13": {
      "Position": {},
      "Rotation": {
        "0": "82A, FFFFFF01, FFFFD817",
        "119": "82A, FFFFFF01, FFFFD817"
      },
      "Scale": {},
      "Vector": {},
      "Vertex": {},
      "Normal": {},
      "Target": {},
      "Roll": {},
      "Angle": {},
      "Color": {},
      "Intensity": {},
      "Spot": {},
      "Point": {},
      "PositionName": null,
      "RotationName": "animation_00033404_mkey_13_rot_0002D2A4",
      "ScaleName": null,
      "VectorName": null,
      "VertexName": null,
      "VertexItemName": null,
      "NormalItemName": null,
      "NormalName": null,
      "TargetName": null,
      "RollName": null,
      "AngleName": null,
      "ColorName": null,
      "IntensityName": null,
      "SpotName": null,
      "PointName": null
    },
    "17": {
      "Position": {},
      "Rotation": {
        "0": "FFFFFD8B, FFFFEEEA, FFFFE40D",
        "119": "FFFFFD8B, FFFFEEEA, FFFFE40D"
      },
      "Scale": {},
      "Vector": {},
      "Vertex": {},
      "Normal": {},
      "Target": {},
      "Roll": {},
      "Angle": {},
      "Color": {},
      "Intensity": {},
      "Spot": {},
      "Point": {},
      "PositionName": null,
      "RotationName": "animation_00033404_mkey_17_rot_0002D2C4",
      "ScaleName": null,
      "VectorName": null,
      "VertexName": null,
      "VertexItemName": null,
      "NormalItemName": null,
      "NormalName": null,
      "TargetName": null,
      "RollName": null,
      "AngleName": null,
      "ColorName": null,
      "IntensityName": null,
      "SpotName": null,
      "PointName": null
    },
    "23": {
      "Position": {},
      "Rotation": {
        "0": "FFFFF398, ADF, FFFFE866",
        "29": "FFFFF398, ADF, FFFFE866",
        "30": "FFFFF384, AB6, FFFFE7BC",
        "31": "FFFFF308, A0C, FFFFE57A",
        "32": "FFFFF386, AB8, FFFFE7C2",
        "33": "FFFFF398, ADF, FFFFE866",
        "34": "FFFFF386, AB8, FFFFE7C2",
        "35": "FFFFF308, A0C, FFFFE57A",
        "36": "FFFFF386, AB8, FFFFE7C2",
        "37": "FFFFF398, ADF, FFFFE866",
        "38": "FFFFF39E, ADD, FFFFE84D",
        "39": "FFFFF354, A75, FFFFE6D7",
        "40": "FFFFF308, A0C, FFFFE57A",
        "41": "FFFFF381, AB2, FFFFE7AE",
        "42": "FFFFF398, ADF, FFFFE866",
        "43": "FFFFF39D, AE2, FFFFE869",
        "44": "FFFFF399, AD4, FFFFE826",
        "45": "FFFFF388, ABA, FFFFE7C9",
        "46": "FFFFF39F, ADE, FFFFE84E",
        "47": "FFFFF398, ADF, FFFFE866",
        "48": "FFFFF39F, ADE, FFFFE84E",
        "49": "FFFFF388, ABA, FFFFE7C9",
        "50": "FFFFF39E, ADD, FFFFE84E",
        "51": "FFFFF398, ADF, FFFFE866",
        "119": "FFFFF398, ADF, FFFFE866"
      },
      "Scale": {},
      "Vector": {},
      "Vertex": {},
      "Normal": {},
      "Target": {},
      "Roll": {},
      "Angle": {},
      "Color": {},
      "Intensity": {},
      "Spot": {},
      "Point": {},
      "PositionName": null,
      "RotationName": "animation_00033404_mkey_23_rot_0002D2E4",
      "ScaleName": null,
      "VectorName": null,
      "VertexName": null,
      "VertexItemName": null,
      "NormalItemName": null,
      "NormalName": null,
      "TargetName": null,
      "RollName": null,
      "AngleName": null,
      "ColorName": null,
      "IntensityName": null,
      "SpotName": null,
      "PointName": null
    },
    "24": {
      "Position": {},
      "Rotation": {
        "0": "0, 0, FFFFDC72",
        "29": "0, 0, FFFFDC72",
        "30": "0, 0, FFFFD5AD",
        "31": "0, 0, FFFFD187",
        "32": "0, 0, FFFFD5C3",
        "33": "0, 0, FFFFDC72",
        "34": "0, 0, FFFFD5C3",
        "35": "0, 0, FFFFD187",
        "36": "0, 0, FFFFD5C3",
        "37": "0, 0, FFFFDC72",
        "38": "0, 0, FFFFD8A1",
        "39": "0, 0, FFFFD375",
        "40": "0, 0, FFFFD187",
        "41": "0, 0, FFFFD57C",
        "42": "0, 0, FFFFDC72",
        "43": "0, 0, FFFFDB41",
        "44": "0, 0, FFFFD7C9",
        "45": "0, 0, FFFFD616",
        "46": "0, 0, FFFFD8F2",
        "47": "0, 0, FFFFDC72",
        "48": "0, 0, FFFFD8F2",
        "49": "0, 0, FFFFD616",
        "50": "0, 0, FFFFD8EC",
        "51": "0, 0, FFFFDC72",
        "119": "0, 0, FFFFDC72"
      },
      "Scale": {},
      "Vector": {},
      "Vertex": {},
      "Normal": {},
      "Target": {},
      "Roll": {},
      "Angle": {},
      "Color": {},
      "Intensity": {},
      "Spot": {},
      "Point": {},
      "PositionName": null,
      "RotationName": "animation_00033404_mkey_24_rot_0002D474",
      "ScaleName": null,
      "VectorName": null,
      "VertexName": null,
      "VertexItemName": null,
      "NormalItemName": null,
      "NormalName": null,
      "TargetName": null,
      "RollName": null,
      "AngleName": null,
      "ColorName": null,
      "IntensityName": null,
      "SpotName": null,
      "PointName": null
    },
    "27": {
      "Position": {},
      "Rotation": {
        "0": "0, 0, 2296",
        "119": "0, 0, 2296"
      },
      "Scale": {},
      "Vector": {},
      "Vertex": {},
      "Normal": {},
      "Target": {},
      "Roll": {},
      "Angle": {},
      "Color": {},
      "Intensity": {},
      "Spot": {},
      "Point": {},
      "PositionName": null,
      "RotationName": "animation_00033404_mkey_27_rot_0002D604",
      "ScaleName": null,
      "VectorName": null,
      "VertexName": null,
      "VertexItemName": null,
      "NormalItemName": null,
      "NormalName": null,
      "TargetName": null,
      "RollName": null,
      "AngleName": null,
      "ColorName": null,
      "IntensityName": null,
      "SpotName": null,
      "PointName": null
    },
    "31": {
      "Position": {},
      "Rotation": {
        "0": "0, 4E3, 0",
        "11": "0, 531, 0",
        "12": "0, 53C, 0",
        "27": "0, 563, 0",
        "28": "0, 556, 0",
        "29": "0, 546, 0",
        "30": "0, 532, 0",
        "31": "0, 51B, 0",
        "32": "0, 501, 0",
        "33": "0, 4E3, 0",
        "34": "0, 4C1, 0",
        "35": "0, 49B, 0",
        "36": "0, 471, 0",
        "37": "0, 443, 0",
        "38": "0, 411, 0",
        "39": "0, 3DD, 0",
        "40": "0, 3A5, 0",
        "41": "0, 36B, 0",
        "42": "0, 32E, 0",
        "43": "0, 2EF, 0",
        "44": "0, 2AD, 0",
        "45": "0, 26A, 0",
        "46": "0, 225, 0",
        "47": "0, 1DF, 0",
        "48": "0, 198, 0",
        "49": "0, 14F, 0",
        "50": "0, 106, 0",
        "51": "0, BD, 0",
        "52": "0, 73, 0",
        "53": "0, 2A, 0",
        "54": "0, FFFFFFE1, 0",
        "55": "0, FFFFFF98, 0",
        "56": "0, FFFFFF50, 0",
        "57": "0, FFFFFF09, 0",
        "58": "0, FFFFFEC3, 0",
        "59": "0, FFFFFE7E, 0",
        "60": "0, FFFFFE3C, 0",
        "61": "0, FFFFFDFA, 0",
        "62": "0, FFFFFDBB, 0",
        "63": "0, FFFFFD7F, 0",
        "64": "0, FFFFFD45, 0",
        "65": "0, FFFFFD0E, 0",
        "66": "0, FFFFFCD9, 0",
        "67": "0, FFFFFCA9, 0",
        "68": "0, FFFFFC7B, 0",
        "69": "0, FFFFFC52, 0",
        "70": "0, FFFFFC2C, 0",
        "71": "0, FFFFFC0A, 0",
        "72": "0, FFFFFBED, 0",
        "73": "0, FFFFFBD4, 0",
        "74": "0, FFFFFBBD, 0",
        "75": "0, FFFFFBA7, 0",
        "76": "0, FFFFFB94, 0",
        "77": "0, FFFFFB83, 0",
        "78": "0, FFFFFB74, 0",
        "79": "0, FFFFFB66, 0",
        "80": "0, FFFFFB5B, 0",
        "119": "0, FFFFFBED, 0"
      },
      "Scale": {},
      "Vector": {},
      "Vertex": {},
      "Normal": {},
      "Target": {},
      "Roll": {},
      "Angle": {},
      "Color": {},
      "Intensity": {},
      "Spot": {},
      "Point": {},
      "PositionName": null,
      "RotationName": "animation_00033404_mkey_31_rot_0002D624",
      "ScaleName": null,
      "VectorName": null,
      "VertexName": null,
      "VertexItemName": null,
      "NormalItemName": null,
      "NormalName": null,
      "TargetName": null,
      "RollName": null,
      "AngleName": null,
      "ColorName": null,
      "IntensityName": null,
      "SpotName": null,
      "PointName": null
    },
    "32": {
      "Position": {},
      "Rotation": {
        "0": "29, FFFFF47F, 3379",
        "1": "0, FFFFF47E, 340C",
        "8": "29, FFFFF46F, 3349",
        "9": "0, FFFFF46B, 33D2",
        "10": "0, FFFFF467, 33C8",
        "11": "29, FFFFF464, 3329",
        "12": "0, FFFFF460, 33B2",
        "13": "0, FFFFF45C, 33A7",
        "14": "29, FFFFF459, 3309",
        "17": "0, FFFFF450, 3382",
        "20": "2A, FFFFF44A, 32DD",
        "21": "0, FFFFF448, 336E",
        "23": "0, FFFFF449, 336E",
        "24": "2A, FFFFF44A, 32DD",
        "25": "0, FFFFF44C, 3377",
        "26": "0, FFFFF44E, 337F",
        "27": "29, FFFFF452, 32F5",
        "28": "29, FFFFF457, 3303",
        "29": "29, FFFFF45D, 3314",
        "30": "0, FFFFF463, 33BC",
        "31": "29, FFFFF46C, 333E",
        "32": "29, FFFFF475, 335A",
        "33": "29, FFFFF47F, 3379",
        "34": "0, FFFFF48B, 344C",
        "35": "28, FFFFF49A, 342B",
        "36": "28, FFFFF4AB, 34CA",
        "37": "0, FFFFF4BD, 361C",
        "38": "0, FFFFF4D0, 36EE",
        "39": "27, FFFFF4E4, 3737",
        "40": "27, FFFFF4F8, 3811",
        "41": "27, FFFFF50A, 38DD",
        "42": "27, FFFFF51A, 398D",
        "43": "26, FFFFF528, 3A15",
        "44": "0, FFFFF534, 3AFD",
        "45": "26, FFFFF53D, 3A7C",
        "46": "0, FFFFF544, 3ADB",
        "47": "0, FFFFF54C, 3A6C",
        "48": "26, FFFFF555, 3938",
        "49": "26, FFFFF561, 3872",
        "50": "25, FFFFF571, 3793",
        "51": "0, FFFFF586, 3737",
        "52": "0, FFFFF59F, 3644",
        "53": "0, FFFFF5BD, 3557",
        "54": "0, FFFFF5DE, 347B",
        "55": "23, FFFFF601, 3326",
        "56": "0, FFFFF623, 331B",
        "57": "0, FFFFF644, 32AA",
        "58": "22, FFFFF661, 31DC",
        "59": "21, FFFFF678, 31DE",
        "60": "0, FFFFF685, 32C5",
        "61": "21, FFFFF688, 32DC",
        "62": "0, FFFFF682, 345F",
        "63": "22, FFFFF674, 34F4",
        "64": "0, FFFFF65F, 36D7",
        "65": "22, FFFFF647, 37AE",
        "66": "23, FFFFF62D, 391E",
        "67": "23, FFFFF612, 3A85",
        "68": "0, FFFFF5FA, 3C62",
        "69": "24, FFFFF5E5, 3CEC",
        "70": "24, FFFFF5D4, 3DCA",
        "71": "0, FFFFF5C9, 3EEC",
        "72": "0, FFFFF5C5, 3F1B",
        "73": "24, FFFFF5C6, 3E7C",
        "74": "24, FFFFF5C8, 3E69",
        "75": "24, FFFFF5CA, 3E4E",
        "76": "24, FFFFF5CD, 3E2B",
        "77": "0, FFFFF5D1, 3E94",
        "78": "24, FFFFF5D6, 3DD0",
        "79": "0, FFFFF5DC, 3E2B",
        "80": "24, FFFFF5E2, 3D5A",
        "81": "0, FFFFF5E9, 3DAA",
        "82": "0, FFFFF5F1, 3D60",
        "83": "23, FFFFF5FA, 3C7F",
        "84": "23, FFFFF603, 3C2C",
        "85": "0, FFFFF60D, 3C68",
        "86": "0, FFFFF617, 3C0C",
        "87": "23, FFFFF622, 3B1A",
        "88": "0, FFFFF62E, 3B4A",
        "89": "0, FFFFF63A, 3AE4",
        "90": "22, FFFFF647, 39E9",
        "91": "22, FFFFF653, 397F",
        "92": "0, FFFFF660, 39A5",
        "93": "22, FFFFF66E, 38A5",
        "94": "21, FFFFF67C, 3836",
        "95": "21, FFFFF68A, 37C6",
        "96": "0, FFFFF697, 37E9",
        "97": "21, FFFFF6A6, 36E6",
        "98": "0, FFFFF6B3, 3709",
        "99": "0, FFFFF6C1, 369B",
        "100": "0, FFFFF6CF, 362D",
        "101": "20, FFFFF6DD, 352F",
        "102": "0, FFFFF6EA, 3557",
        "103": "20, FFFFF6F8, 345D",
        "104": "0, FFFFF704, 3489",
        "105": "0, FFFFF711, 3426",
        "106": "1F, FFFFF71D, 3335",
        "107": "0, FFFFF728, 336B",
        "108": "0, FFFFF733, 3313",
        "109": "1F, FFFFF73E, 322D",
        "110": "0, FFFFF748, 3270",
        "111": "0, FFFFF752, 3225",
        "112": "1E, FFFFF75B, 314D",
        "113": "1E, FFFFF761, 311C",
        "114": "0, FFFFF762, 319C",
        "115": "1E, FFFFF760, 310E",
        "116": "0, FFFFF75C, 31B1",
        "117": "0, FFFFF758, 31C7",
        "118": "1E, FFFFF754, 3149",
        "119": "1E, FFFFF753, 3152"
      },
      "Scale": {},
      "Vector": {},
      "Vertex": {},
      "Normal": {},
      "Target": {},
      "Roll": {},
      "Angle": {},
      "Color": {},
      "Intensity": {},
      "Spot": {},
      "Point": {},
      "PositionName": null,
      "RotationName": "animation_00033404_mkey_32_rot_0002D9C4",
      "ScaleName": null,
      "VectorName": null,
      "VertexName": null,
      "VertexItemName": null,
      "NormalItemName": null,
      "NormalName": null,
      "TargetName": null,
      "RollName": null,
      "AngleName": null,
      "ColorName": null,
      "IntensityName": null,
      "SpotName": null,
      "PointName": null
    },
    "33": {
      "Position": {},
      "Rotation": {
        "0": "0, 0, FC",
        "1": "0, 0, 0",
        "7": "0, 0, 0",
        "8": "0, 0, FC",
        "9": "0, 0, 0",
        "10": "0, 0, 0",
        "11": "0, 0, FC",
        "12": "0, 0, 0",
        "13": "0, 0, 0",
        "14": "0, 0, FC",
        "16": "0, 0, FC",
        "17": "0, 0, 0",
        "19": "0, 0, 0",
        "20": "0, 0, FC",
        "21": "0, 0, 0",
        "23": "0, 0, 0",
        "24": "0, 0, FD",
        "25": "0, 0, 0",
        "26": "0, 0, 0",
        "27": "0, 0, FC",
        "29": "0, 0, FC",
        "30": "0, 0, 0",
        "31": "0, 0, FD",
        "33": "0, 0, FD",
        "34": "0, 0, 0",
        "35": "0, 0, FD",
        "36": "0, 0, FC",
        "37": "0, 0, 0",
        "38": "0, 0, 0",
        "39": "0, 0, FD",
        "43": "0, 0, FC",
        "44": "0, 0, 0",
        "45": "0, 0, FC",
        "46": "0, 0, 0",
        "47": "0, 0, 0",
        "48": "0, 0, FD",
        "50": "0, 0, FC",
        "51": "0, 0, 0",
        "54": "0, 0, 0",
        "55": "0, 0, FC",
        "56": "0, 0, 0",
        "57": "0, 0, 0",
        "58": "0, 0, FC",
        "59": "0, 0, FC",
        "60": "0, 0, 0",
        "61": "0, 0, FD",
        "62": "0, 0, 0",
        "63": "0, 0, FC",
        "64": "0, 0, 0",
        "65": "0, 0, FD",
        "67": "0, 0, FC",
        "68": "0, 0, 0",
        "69": "0, 0, FC",
        "70": "0, 0, FD",
        "71": "0, 0, 0",
        "72": "0, 0, 0",
        "73": "0, 0, FD",
        "76": "0, 0, FD",
        "77": "0, 0, 0",
        "78": "0, 0, FC",
        "79": "0, 0, 0",
        "80": "0, 0, FC",
        "81": "0, 0, 0",
        "82": "0, 0, 0",
        "83": "0, 0, FD",
        "84": "0, 0, FC",
        "85": "0, 0, 0",
        "86": "0, 0, 0",
        "87": "0, 0, FC",
        "88": "0, 0, 0",
        "89": "0, 0, 0",
        "90": "0, 0, FD",
        "91": "0, 0, FD",
        "92": "0, 0, 0",
        "93": "0, 0, FC",
        "95": "0, 0, FD",
        "96": "0, 0, 0",
        "97": "0, 0, FD",
        "98": "0, 0, 0",
        "100": "0, 0, 0",
        "101": "0, 0, FC",
        "102": "0, 0, 0",
        "103": "0, 0, FC",
        "104": "0, 0, 0",
        "105": "0, 0, 0",
        "106": "0, 0, FC",
        "107": "0, 0, 0",
        "108": "0, 0, 0",
        "109": "0, 0, FC",
        "110": "0, 0, 0",
        "111": "0, 0, 0",
        "112": "0, 0, FC",
        "113": "0, 0, FC",
        "114": "0, 0, 0",
        "115": "0, 0, FC",
        "116": "0, 0, 0",
        "117": "0, 0, 0",
        "118": "0, 0, FD",
        "119": "0, 0, FD"
      },
      "Scale": {},
      "Vector": {},
      "Vertex": {},
      "Normal": {},
      "Target": {},
      "Roll": {},
      "Angle": {},
      "Color": {},
      "Intensity": {},
      "Spot": {},
      "Point": {},
      "PositionName": null,
      "RotationName": "animation_00033404_mkey_33_rot_0002E094",
      "ScaleName": null,
      "VectorName": null,
      "VertexName": null,
      "VertexItemName": null,
      "NormalItemName": null,
      "NormalName": null,
      "TargetName": null,
      "RollName": null,
      "AngleName": null,
      "ColorName": null,
      "IntensityName": null,
      "SpotName": null,
      "PointName": null
    },
    "37": {
      "Position": {},
      "Rotation": {
        "0": "FFFFE70B, FFFFECFE, FFFF94F9",
        "1": "FFFFE6EF, FFFFED10, FFFF958D",
        "5": "FFFFE70F, FFFFECFA, FFFF9583",
        "6": "FFFFE71C, FFFFECF1, FFFF957F",
        "7": "FFFFE72B, FFFFECE7, FFFF957B",
        "8": "FFFFE758, FFFFECCA, FFFF94E1",
        "9": "FFFFE74B, FFFFECD1, FFFF9571",
        "10": "FFFFE75C, FFFFECC6, FFFF956B",
        "11": "FFFFE78A, FFFFECA8, FFFF94D1",
        "12": "FFFFE77E, FFFFECAE, FFFF9560",
        "13": "FFFFE790, FFFFECA3, FFFF955B",
        "14": "FFFFE7BD, FFFFEC86, FFFF94C0",
        "15": "FFFFE7CD, FFFFEC7B, FFFF94BB",
        "16": "FFFFE7DB, FFFFEC72, FFFF94B6",
        "17": "FFFFE7CB, FFFFEC7B, FFFF9548",
        "18": "FFFFE7D6, FFFFEC73, FFFF9544",
        "19": "FFFFE7E0, FFFFEC6D, FFFF9541",
        "20": "FFFFE804, FFFFEC57, FFFF94A9",
        "21": "FFFFE7EB, FFFFEC66, FFFF953D",
        "23": "FFFFE7EB, FFFFEC66, FFFF953D",
        "24": "FFFFE803, FFFFEC57, FFFF94A9",
        "25": "FFFFE7DD, FFFFEC6F, FFFF9542",
        "26": "FFFFE7D0, FFFFEC77, FFFF9546",
        "27": "FFFFE7DC, FFFFEC71, FFFF94B6",
        "28": "FFFFE7C7, FFFFEC80, FFFF94BD",
        "29": "FFFFE7AC, FFFFEC91, FFFF94C6",
        "30": "FFFFE76F, FFFFECB9, FFFF9565",
        "31": "FFFFE767, FFFFECC0, FFFF94DC",
        "32": "FFFFE73C, FFFFECDD, FFFF94E9",
        "33": "FFFFE70B, FFFFECFE, FFFF94F9",
        "34": "FFFFE6B9, FFFFED3F, FFFF9587",
        "35": "FFFFE6A1, FFFFED6B, FFFF94C5",
        "36": "FFFFE66A, FFFFEDB9, FFFF9477",
        "37": "FFFFE614, FFFFEE27, FFFF94A4",
        "38": "FFFFE5DA, FFFFEE8C, FFFF942A",
        "39": "FFFFE5BC, FFFFEEE5, FFFF9313",
        "40": "FFFFE57E, FFFFEF54, FFFF928D",
        "41": "FFFFE53F, FFFFEFC3, FFFF920D",
        "42": "FFFFE501, FFFFF02D, FFFF9199",
        "43": "FFFFE4C6, FFFFF08F, FFFF913B",
        "44": "FFFFE470, FFFFF0F7, FFFF918B",
        "45": "FFFFE45F, FFFFF127, FFFF90E0",
        "46": "FFFFE417, FFFFF16D, FFFF9181",
        "47": "FFFFE3F2, FFFFF192, FFFF91B9",
        "48": "FFFFE3EC, FFFFF199, FFFF9185",
        "49": "FFFFE3C3, FFFFF1AC, FFFF9203",
        "50": "FFFFE392, FFFFF1BD, FFFF929D",
        "51": "FFFFE338, FFFFF1E2, FFFF93E1",
        "52": "FFFFE2EE, FFFFF1F5, FFFF94AC",
        "53": "FFFFE293, FFFFF20C, FFFF9589",
        "54": "FFFFE224, FFFFF229, FFFF9676",
        "55": "FFFFE1BB, FFFFF237, FFFF96E1",
        "56": "FFFFE0FD, FFFFF279, FFFF9877",
        "57": "FFFFE03F, FFFFF2B1, FFFF9985",
        "58": "FFFFDF7D, FFFFF2DE, FFFF9A0A",
        "59": "FFFFDE7C, FFFFF332, FFFF9B1F",
        "60": "FFFFDD19, FFFFF3CA, FFFF9D19",
        "61": "FFFFDBA5, FFFFF463, FFFF9E87",
        "62": "FFFFD9F5, FFFFF543, FFFFA157",
        "63": "FFFFD8AC, FFFFF5CD, FFFFA331",
        "64": "FFFFD797, FFFFF635, FFFFA603",
        "65": "FFFFD725, FFFFF5EB, FFFFA7A6",
        "66": "FFFFD713, FFFFF52E, FFFFA985",
        "67": "FFFFD75A, FFFFF401, FFFFAB11",
        "68": "FFFFD7C5, FFFFF28E, FFFFACAE",
        "69": "FFFFD845, FFFFF0DD, FFFFACF1",
        "70": "FFFFD875, FFFFEF65, FFFFAD72",
        "71": "FFFFD813, FFFFEE5D, FFFFAE5E",
        "72": "FFFFD6EF, FFFFEDDF, FFFFAEEC",
        "73": "FFFFD4CA, FFFFEDF9, FFFFAF0A",
        "74": "FFFFD195, FFFFEE91, FFFFAF5D",
        "75": "FFFFCD7F, FFFFEF57, FFFFAF2A",
        "76": "FFFFC8BA, FFFFEFEB, FFFFAE48",
        "77": "FFFFC379, FFFFEFE8, FFFFAD3D",
        "78": "FFFFBE41, FFFFEED9, FFFFAB0E",
        "79": "FFFFB91E, FFFFECD4, FFFFAA03",
        "80": "FFFFB480, FFFFE9E1, FFFFA8CA",
        "81": "FFFFB010, FFFFE67A, FFFFA96D",
        "82": "FFFFABE1, FFFFE2DF, FFFFAAAB",
        "83": "FFFFA7C7, FFFFDF60, FFFFAC76",
        "84": "FFFFA380, FFFFDC4D, FFFFAF9A",
        "85": "FFFF9F1F, FFFFD9D9, FFFFB3D7",
        "86": "FFFF9C93, FFFFD889, FFFFB656",
        "87": "FFFF9CED, FFFFD867, FFFFB5DB",
        "88": "FFFF9E7E, FFFFD905, FFFFB533",
        "89": "FFFF9FF4, FFFFD9B4, FFFFB473",
        "90": "FFFF9FF9, FFFFD9D4, FFFFB4DA",
        "91": "FFFF9DB4, FFFFD956, FFFFB7D9",
        "92": "FFFF99CC, FFFFD8AC, FFFFBCD7",
        "93": "FFFF9541, FFFFD7FB, FFFFC1D3",
        "94": "FFFF9126, FFFFD7A0, FFFFC6FE",
        "95": "FFFF8F1B, FFFFD77D, FFFFCA48",
        "96": "FFFF8ECA, FFFFD72D, FFFFCC9D",
        "97": "FFFF8F21, FFFFD662, FFFFCDD6",
        "98": "FFFF904A, FFFFD593, FFFFCF2E",
        "99": "FFFF9350, FFFFD50E, FFFFCE16",
        "100": "FFFF9928, FFFFD5A8, FFFFC9C3",
        "101": "FFFFA060, FFFFD79C, FFFFC374",
        "102": "FFFFA6C3, FFFFDA54, FFFFBF10",
        "103": "FFFFAC58, FFFFDD50, FFFFBB0E",
        "104": "FFFFB13A, FFFFE0AB, FFFFB902",
        "105": "FFFFB5B8, FFFFE3FB, FFFFB782",
        "106": "FFFFBA07, FFFFE70E, FFFFB668",
        "107": "FFFFBE2F, FFFFE9DD, FFFFB6DF",
        "108": "FFFFC263, FFFFEC11, FFFFB766",
        "109": "FFFFC69D, FFFFED8E, FFFFB7C4",
        "110": "FFFFCAB5, FFFFEE76, FFFFB916",
        "111": "FFFFCE9F, FFFFEEAF, FFFFB9CF",
        "112": "FFFFD234, FFFFEE5E, FFFFB9C7",
        "113": "FFFFD52C, FFFFEDCD, FFFFB9C1",
        "114": "FFFFD770, FFFFED30, FFFFB9C9",
        "115": "FFFFD91B, FFFFEC85, FFFFB8AF",
        "116": "FFFFDA3E, FFFFEC01, FFFFB872",
        "117": "FFFFDAF3, FFFFEB94, FFFFB7D3",
        "118": "FFFFDB50, FFFFEB47, FFFFB6F0",
        "119": "FFFFDB69, FFFFEB2E, FFFFB6C6"
      },
      "Scale": {},
      "Vector": {},
      "Vertex": {},
      "Normal": {},
      "Target": {},
      "Roll": {},
      "Angle": {},
      "Color": {},
      "Intensity": {},
      "Spot": {},
      "Point": {},
      "PositionName": null,
      "RotationName": "animation_00033404_mkey_37_rot_0002E6C4",
      "ScaleName": null,
      "VectorName": null,
      "VertexName": null,
      "VertexItemName": null,
      "NormalItemName": null,
      "NormalName": null,
      "TargetName": null,
      "RollName": null,
      "AngleName": null,
      "ColorName": null,
      "IntensityName": null,
      "SpotName": null,
      "PointName": null
    },
    "38": {
      "Position": {},
      "Rotation": {
        "0": "0, 0, FFFFC93B",
        "1": "0, 0, FFFFC929",
        "8": "0, 0, FFFFC959",
        "9": "0, 0, FFFFC94D",
        "10": "0, 0, FFFFC953",
        "11": "0, 0, FFFFC96D",
        "12": "0, 0, FFFFC961",
        "13": "0, 0, FFFFC967",
        "14": "0, 0, FFFFC980",
        "17": "0, 0, FFFFC97E",
        "19": "0, 0, FFFFC986",
        "20": "0, 0, FFFFC99B",
        "21": "0, 0, FFFFC98A",
        "23": "0, 0, FFFFC98A",
        "24": "0, 0, FFFFC99B",
        "25": "0, 0, FFFFC985",
        "26": "0, 0, FFFFC980",
        "27": "0, 0, FFFFC98C",
        "30": "0, 0, FFFFC95B",
        "31": "0, 0, FFFFC95F",
        "32": "0, 0, FFFFC94E",
        "33": "0, 0, FFFFC93B",
        "34": "0, 0, FFFFC90C",
        "35": "0, 0, FFFFC8F0",
        "36": "0, 0, FFFFC8B4",
        "37": "0, 0, FFFFC859",
        "38": "0, 0, FFFFC809",
        "39": "0, 0, FFFFC7C4",
        "40": "0, 0, FFFFC76A",
        "41": "0, 0, FFFFC710",
        "42": "0, 0, FFFFC6B9",
        "43": "0, 0, FFFFC66B",
        "44": "0, 0, FFFFC616",
        "45": "0, 0, FFFFC5F9",
        "46": "0, 0, FFFFC5C8",
        "47": "0, 0, FFFFC5BD",
        "48": "0, 0, FFFFC5D5",
        "49": "0, 0, FFFFC5E7",
        "50": "0, 0, FFFFC604",
        "51": "0, 0, FFFFC618",
        "52": "0, 0, FFFFC645",
        "53": "0, 0, FFFFC675",
        "54": "0, 0, FFFFC6A5",
        "55": "0, 0, FFFFC6E4",
        "56": "0, 0, FFFFC6FF",
        "57": "0, 0, FFFFC727",
        "58": "0, 0, FFFFC757",
        "59": "0, 0, FFFFC776",
        "60": "0, 0, FFFFC7A5",
        "61": "0, 0, FFFFC834",
        "62": "0, 0, FFFFC910",
        "63": "0, 0, FFFFCA6A",
        "64": "0, 0, FFFFCC2F",
        "65": "0, 0, FFFFCE5E",
        "66": "0, 0, FFFFD0DE",
        "67": "0, 0, FFFFD384",
        "68": "0, 0, FFFFD63A",
        "69": "0, 0, FFFFD8D2",
        "70": "0, 0, FFFFDB18",
        "71": "0, 0, FFFFDCD6",
        "72": "0, 0, FFFFDDC4",
        "73": "0, 0, FFFFDDD8",
        "74": "0, 0, FFFFDD66",
        "75": "0, 0, FFFFDC9B",
        "76": "0, 0, FFFFDBAE",
        "77": "0, 0, FFFFDADC",
        "78": "0, 0, FFFFDA2D",
        "79": "0, 0, FFFFD9EF",
        "80": "0, 0, FFFFDA06",
        "81": "0, 0, FFFFDAA6",
        "82": "0, 0, FFFFDBA8",
        "83": "0, 0, FFFFDCF9",
        "84": "0, 0, FFFFDE96",
        "85": "0, 0, FFFFE05C",
        "86": "0, 0, FFFFE176",
        "87": "0, 0, FFFFE171",
        "88": "0, 0, FFFFE0F0",
        "89": "0, 0, FFFFE058",
        "90": "0, 0, FFFFE022",
        "91": "0, 0, FFFFE067",
        "92": "0, 0, FFFFE0FC",
        "93": "0, 0, FFFFE1DF",
        "94": "0, 0, FFFFE308",
        "95": "0, 0, FFFFE417",
        "96": "0, 0, FFFFE5A0",
        "97": "0, 0, FFFFE7C7",
        "98": "0, 0, FFFFEA0A",
        "99": "0, 0, FFFFEB3C",
        "100": "0, 0, FFFFEA4A",
        "101": "0, 0, FFFFE7AD",
        "102": "0, 0, FFFFE518",
        "103": "0, 0, FFFFE2A7",
        "104": "0, 0, FFFFE070",
        "105": "0, 0, FFFFDE7C",
        "106": "0, 0, FFFFDCDB",
        "107": "0, 0, FFFFDBB2",
        "108": "0, 0, FFFFDAEC",
        "109": "0, 0, FFFFDA88",
        "110": "0, 0, FFFFDAA0",
        "111": "0, 0, FFFFDB09",
        "112": "0, 0, FFFFDBB3",
        "113": "0, 0, FFFFDCA1",
        "114": "0, 0, FFFFDDB4",
        "115": "0, 0, FFFFDEA7",
        "116": "0, 0, FFFFDF99",
        "117": "0, 0, FFFFE04E",
        "118": "0, 0, FFFFE0B6",
        "119": "0, 0, FFFFE0E0"
      },
      "Scale": {},
      "Vector": {},
      "Vertex": {},
      "Normal": {},
      "Target": {},
      "Roll": {},
      "Angle": {},
      "Color": {},
      "Intensity": {},
      "Spot": {},
      "Point": {},
      "PositionName": null,
      "RotationName": "animation_00033404_mkey_38_rot_0002EE04",
      "ScaleName": null,
      "VectorName": null,
      "VertexName": null,
      "VertexItemName": null,
      "NormalItemName": null,
      "NormalName": null,
      "TargetName": null,
      "RollName": null,
      "AngleName": null,
      "ColorName": null,
      "IntensityName": null,
      "SpotName": null,
      "PointName": null
    },
    "39": {
      "Position": {},
      "Rotation": {
        "0": "0, 0, FFFFC67D",
        "1": "0, 0, FFFFC669",
        "8": "0, 0, FFFFC69D",
        "9": "0, 0, FFFFC690",
        "10": "0, 0, FFFFC697",
        "11": "0, 0, FFFFC6B2",
        "12": "0, 0, FFFFC6A5",
        "13": "0, 0, FFFFC6AD",
        "14": "0, 0, FFFFC6C8",
        "17": "0, 0, FFFFC6C6",
        "19": "0, 0, FFFFC6CE",
        "20": "0, 0, FFFFC6E6",
        "21": "0, 0, FFFFC6D3",
        "23": "0, 0, FFFFC6D3",
        "24": "0, 0, FFFFC6E5",
        "25": "0, 0, FFFFC6CD",
        "26": "0, 0, FFFFC6C8",
        "27": "0, 0, FFFFC6D5",
        "28": "0, 0, FFFFC6CC",
        "29": "0, 0, FFFFC6C1",
        "30": "0, 0, FFFFC69F",
        "31": "0, 0, FFFFC6A4",
        "32": "0, 0, FFFFC691",
        "33": "0, 0, FFFFC67D",
        "34": "0, 0, FFFFC649",
        "35": "0, 0, FFFFC62B",
        "36": "0, 0, FFFFC5E9",
        "37": "0, 0, FFFFC587",
        "38": "0, 0, FFFFC52D",
        "39": "0, 0, FFFFC4E3",
        "40": "0, 0, FFFFC481",
        "41": "0, 0, FFFFC420",
        "42": "0, 0, FFFFC3C4",
        "43": "0, 0, FFFFC371",
        "44": "0, 0, FFFFC316",
        "45": "0, 0, FFFFC2F7",
        "46": "0, 0, FFFFC2C4",
        "47": "0, 0, FFFFC2B8",
        "48": "0, 0, FFFFC2D1",
        "49": "0, 0, FFFFC2E4",
        "50": "0, 0, FFFFC303",
        "51": "0, 0, FFFFC318",
        "52": "0, 0, FFFFC348",
        "53": "0, 0, FFFFC37B",
        "54": "0, 0, FFFFC3AE",
        "55": "0, 0, FFFFC3F1",
        "56": "0, 0, FFFFC40F",
        "57": "0, 0, FFFFC439",
        "58": "0, 0, FFFFC46D",
        "59": "0, 0, FFFFC48E",
        "60": "0, 0, FFFFC4C1",
        "61": "0, 0, FFFFC55C",
        "62": "0, 0, FFFFC64D",
        "63": "0, 0, FFFFC7CC",
        "64": "0, 0, FFFFC9C0",
        "65": "0, 0, FFFFCC36",
        "66": "0, 0, FFFFCF04",
        "67": "0, 0, FFFFD204",
        "68": "0, 0, FFFFD52A",
        "69": "0, 0, FFFFD814",
        "70": "0, 0, FFFFDAA4",
        "71": "0, 0, FFFFDC9A",
        "72": "0, 0, FFFFDDA4",
        "73": "0, 0, FFFFDDBB",
        "74": "0, 0, FFFFDD3B",
        "75": "0, 0, FFFFDC57",
        "76": "0, 0, FFFFDB4C",
        "77": "0, 0, FFFFDA60",
        "78": "0, 0, FFFFD99C",
        "79": "0, 0, FFFFD955",
        "80": "0, 0, FFFFD96F",
        "81": "0, 0, FFFFDA24",
        "82": "0, 0, FFFFDB46",
        "83": "0, 0, FFFFDCC1",
        "84": "0, 0, FFFFDE90",
        "85": "0, 0, FFFFE08E",
        "86": "0, 0, FFFFE1C8",
        "87": "0, 0, FFFFE1C3",
        "88": "0, 0, FFFFE132",
        "89": "0, 0, FFFFE089",
        "90": "0, 0, FFFFE04D",
        "91": "0, 0, FFFFE099",
        "92": "0, 0, FFFFE140",
        "93": "0, 0, FFFFE23D",
        "94": "0, 0, FFFFE396",
        "95": "0, 0, FFFFE4C2",
        "96": "0, 0, FFFFE673",
        "97": "0, 0, FFFFE8D0",
        "98": "0, 0, FFFFEB49",
        "99": "0, 0, FFFFEC98",
        "100": "0, 0, FFFFEB92",
        "101": "0, 0, FFFFE8B3",
        "102": "0, 0, FFFFE5DE",
        "103": "0, 0, FFFFE320",
        "104": "0, 0, FFFFE0A3",
        "105": "0, 0, FFFFDE73",
        "106": "0, 0, FFFFDC9F",
        "107": "0, 0, FFFFDB51",
        "108": "0, 0, FFFFDA73",
        "109": "0, 0, FFFFDA02",
        "110": "0, 0, FFFFDA1D",
        "111": "0, 0, FFFFDA93",
        "112": "0, 0, FFFFDB52",
        "113": "0, 0, FFFFDC5E",
        "114": "0, 0, FFFFDD93",
        "115": "0, 0, FFFFDEA4",
        "116": "0, 0, FFFFDFB3",
        "117": "0, 0, FFFFE07E",
        "118": "0, 0, FFFFE0F2",
        "119": "0, 0, FFFFE121"
      },
      "Scale": {},
      "Vector": {},
      "Vertex": {},
      "Normal": {},
      "Target": {},
      "Roll": {},
      "Angle": {},
      "Color": {},
      "Intensity": {},
      "Spot": {},
      "Point": {},
      "PositionName": null,
      "RotationName": "animation_00033404_mkey_39_rot_0002F4C4",
      "ScaleName": null,
      "VectorName": null,
      "VertexName": null,
      "VertexItemName": null,
      "NormalItemName": null,
      "NormalName": null,
      "TargetName": null,
      "RollName": null,
      "AngleName": null,
      "ColorName": null,
      "IntensityName": null,
      "SpotName": null,
      "PointName": null
    },
    "41": {
      "Position": {},
      "Rotation": {
        "0": "FFFFF3EF, 1F79, 19F1",
        "1": "FFFFF3E2, 1F81, 19E7",
        "8": "FFFFF404, 1F6E, 1A09",
        "10": "FFFFF400, 1F70, 1A0A",
        "11": "FFFFF412, 1F66, 1A19",
        "13": "FFFFF40D, 1F69, 1A1B",
        "14": "FFFFF41F, 1F5F, 1A29",
        "20": "FFFFF431, 1F55, 1A3E",
        "21": "FFFFF425, 1F5C, 1A37",
        "23": "FFFFF425, 1F5C, 1A37",
        "24": "FFFFF431, 1F55, 1A3E",
        "25": "FFFFF422, 1F5E, 1A32",
        "30": "FFFFF405, 1F6D, 1A10",
        "31": "FFFFF409, 1F6B, 1A0E",
        "32": "FFFFF3FD, 1F72, 1A00",
        "33": "FFFFF3EF, 1F79, 19F1",
        "34": "FFFFF3CC, 1F86, 19B7",
        "35": "FFFFF3B8, 1F7E, 195A",
        "36": "FFFFF38B, 1F79, 18C3",
        "37": "FFFFF343, 1F77, 17FA",
        "38": "FFFFF302, 1F69, 171E",
        "39": "FFFFF2CF, 1F4D, 1638",
        "40": "FFFFF287, 1F35, 1539",
        "41": "FFFFF240, 1F17, 1438",
        "42": "FFFFF1FF, 1EF4, 133E",
        "43": "FFFFF1CB, 1ECC, 1255",
        "44": "FFFFF18E, 1EA6, 1178",
        "45": "FFFFF19A, 1E6C, 10D7",
        "46": "FFFFF18D, 1E40, 1043",
        "47": "FFFFF1AD, 1E0E, FE2",
        "48": "FFFFF1F4, 1DDB, FB4",
        "49": "FFFFF228, 1DB7, F9C",
        "50": "FFFFF25D, 1D9E, FA7",
        "51": "FFFFF273, 1D9B, FC7",
        "52": "FFFFF297, 1DA0, 101C",
        "53": "FFFFF2AE, 1DB8, 109C",
        "54": "FFFFF2B3, 1DE5, 1148",
        "55": "FFFFF2C0, 1E22, 1239",
        "56": "FFFFF28F, 1E89, 1337",
        "57": "FFFFF26C, 1F06, 1482",
        "58": "FFFFF25D, 1F9A, 1626",
        "59": "FFFFF243, 205B, 17F6",
        "60": "FFFFF29E, 2189, 1AE5",
        "61": "FFFFF48D, 22F2, 2041",
        "62": "FFFFF85B, 241E, 2791",
        "63": "FFFFFE0D, 23DA, 30B2",
        "64": "40C, 21AD, 3995",
        "65": "890, 1D5D, 40E0",
        "66": "B13, 17C8, 45DB",
        "67": "BF0, 11B1, 490E",
        "68": "BCE, BC5, 4ADB",
        "69": "B17, 672, 4C03",
        "70": "A3B, 21F, 4C53",
        "71": "96C, FFFFFF1D, 4BE0",
        "72": "8C0, FFFFFDC1, 4B11",
        "73": "845, FFFFFE31, 49FB",
        "74": "806, 47, 4886",
        "75": "808, 3F9, 4740",
        "76": "84F, 935, 46AF",
        "77": "8E6, FD1, 473D",
        "78": "99E, 176E, 49A1",
        "79": "AD9, 1FAC, 4D92",
        "80": "CAB, 280C, 536B",
        "81": "10F7, 302D, 5BE1",
        "82": "1CF9, 3759, 6C0C",
        "83": "4581, 3ACF, 9845",
        "84": "FFFFE6B9, 48A7, 3C40",
        "85": "FFFFEF4C, 4D3E, 46A1",
        "86": "FFFFF1C3, 4FCF, 49F1",
        "87": "FFFFF283, 4FE5, 4AD8",
        "88": "FFFFF21F, 4EB4, 4A11",
        "89": "FFFFF168, 4D4D, 4914",
        "90": "FFFFF113, 4CD9, 4909",
        "91": "FFFFF004, 4D6B, 48FF",
        "92": "FFFFEDC0, 4E31, 47FB",
        "93": "FFFFEBDC, 4EF5, 4725",
        "94": "FFFFEAB8, 4FB2, 4626",
        "95": "FFFFECA3, 511B, 47C4",
        "96": "FFFFEFCF, 5266, 48D8",
        "97": "FFFFF0CF, 50AD, 4542",
        "98": "FFFFEDDF, 4C5C, 3C36",
        "99": "FFFFE5B1, 47E8, 2F17",
        "100": "FFFFC96D, 44C9, 1078",
        "101": "FFFFA25A, 46A0, FFFFE91A",
        "102": "FFFF94A9, 4B84, FFFFDADB",
        "103": "FFFF8F98, 5120, FFFFD54B",
        "104": "FFFF8D7C, 56F7, FFFFD268",
        "105": "FFFF8C4C, 5CE2, FFFFD08A",
        "106": "FFFF8B77, 62C2, FFFFCF44",
        "107": "FFFF8AD6, 6877, FFFFCE29",
        "108": "FFFF8A23, 6DE6, FFFFCD86",
        "109": "FFFF895E, 72EC, FFFFCD71",
        "110": "FFFF889D, 7765, FFFFCD81",
        "111": "FFFF87E6, 7B3C, FFFFCE0F",
        "112": "FFFF8758, 7E65, FFFFCEF6",
        "113": "FFFF8707, 805D, FFFFCF7A",
        "114": "FFFF86E9, 80F5, FFFFCF40",
        "115": "FFFF86F7, 809F, FFFFCED0",
        "116": "FFFF871C, 7FC0, FFFFCDBC",
        "117": "FFFF874C, 7EB5, FFFFCCB9",
        "118": "FFFF8777, 7DD6, FFFFCC0F",
        "119": "FFFF8788, 7D79, FFFFCBBA"
      },
      "Scale": {},
      "Vector": {},
      "Vertex": {},
      "Normal": {},
      "Target": {},
      "Roll": {},
      "Angle": {},
      "Color": {},
      "Intensity": {},
      "Spot": {},
      "Point": {},
      "PositionName": null,
      "RotationName": "animation_00033404_mkey_41_rot_0002FBA4",
      "ScaleName": null,
      "VectorName": null,
      "VertexName": null,
      "VertexItemName": null,
      "NormalItemName": null,
      "NormalName": null,
      "TargetName": null,
      "RollName": null,
      "AngleName": null,
      "ColorName": null,
      "IntensityName": null,
      "SpotName": null,
      "PointName": null
    },
    "44": {
      "Position": {},
      "Rotation": {
        "0": "1B24, FFFFF2E4, 49B2",
        "1": "1B28, FFFFF2E3, 4A20",
        "4": "1B46, FFFFF2EB, 4A30",
        "5": "1B57, FFFFF2EF, 4A39",
        "6": "1B6A, FFFFF2F4, 4A43",
        "7": "1B7F, FFFFF2FA, 4A4E",
        "8": "1B94, FFFFF301, 49ED",
        "9": "1BAE, FFFFF306, 4A67",
        "10": "1BC7, FFFFF30C, 4A74",
        "11": "1BDF, FFFFF314, 4A15",
        "12": "1BFA, FFFFF319, 4A8F",
        "13": "1C13, FFFFF320, 4A9C",
        "14": "1C29, FFFFF327, 4A3C",
        "15": "1C40, FFFFF32D, 4A48",
        "16": "1C55, FFFFF332, 4A53",
        "17": "1C69, FFFFF336, 4ACA",
        "18": "1C7A, FFFFF33A, 4AD3",
        "19": "1C87, FFFFF33E, 4ADA",
        "20": "1C8F, FFFFF342, 4A72",
        "21": "1C97, FFFFF342, 4AE2",
        "23": "1C97, FFFFF342, 4AE2",
        "24": "1C8E, FFFFF341, 4A71",
        "25": "1C83, FFFFF33D, 4AD8",
        "26": "1C71, FFFFF338, 4ACE",
        "27": "1C56, FFFFF333, 4A54",
        "28": "1C36, FFFFF32B, 4A43",
        "29": "1C10, FFFFF321, 4A2F",
        "30": "1BE3, FFFFF313, 4A83",
        "31": "1BAB, FFFFF307, 49F9",
        "32": "1B6C, FFFFF2F6, 49D8",
        "33": "1B24, FFFFF2E4, 49B1",
        "34": "1AD7, FFFFF2D3, 49D7",
        "35": "1A83, FFFFF2CE, 48EC",
        "36": "1A2C, FFFFF2CD, 4841",
        "37": "19D2, FFFFF2CE, 47E1",
        "38": "1970, FFFFF2D1, 46FC",
        "39": "1906, FFFFF2D4, 459F",
        "40": "1897, FFFFF2D1, 44AE",
        "41": "1821, FFFFF2C8, 43C9",
        "42": "17A4, FFFFF2B6, 42FE",
        "43": "1720, FFFFF29A, 4259",
        "44": "1695, FFFFF26F, 4255",
        "45": "15FC, FFFFF238, 41BA",
        "46": "155F, FFFFF1F1, 423D",
        "47": "14B6, FFFFF1A1, 428D",
        "48": "1400, FFFFF14A, 42A0",
        "49": "1343, FFFFF0EB, 4344",
        "50": "127A, FFFFF087, 4403",
        "51": "11AA, FFFFF020, 453F",
        "52": "10CE, FFFFEFBB, 4615",
        "53": "FEB, FFFFEF58, 46E7",
        "54": "F02, FFFFEEF9, 47AC",
        "55": "E16, FFFFEEA0, 47EE",
        "56": "D2E, FFFFEE4A, 48EA",
        "57": "C49, FFFFEDFD, 4950",
        "58": "B69, FFFFEDB8, 4918",
        "59": "A97, FFFFED7A, 4912",
        "60": "9D8, FFFFED43, 492B",
        "61": "927, FFFFED19, 4817",
        "62": "88C, FFFFECF3, 4797",
        "63": "7FC, FFFFECD8, 4605",
        "64": "77E, FFFFECBF, 4521",
        "65": "705, FFFFECAE, 4348",
        "66": "6FB, FFFFEC45, 4176",
        "67": "7A8, FFFFEB46, 3F0A",
        "68": "8F3, FFFFE9DA, 3CA0",
        "69": "AAF, FFFFE83A, 392E",
        "70": "D5A, FFFFE697, 363D",
        "71": "FD5, FFFFE528, 3424",
        "72": "11AC, FFFFE420, 327B",
        "73": "125C, FFFFE3AE, 317B",
        "74": "125A, FFFFE394, 3173",
        "75": "1253, FFFFE37E, 3175",
        "76": "1248, FFFFE36B, 3180",
        "77": "123E, FFFFE359, 31FE",
        "78": "1223, FFFFE34D, 31B4",
        "79": "120F, FFFFE33E, 3245",
        "80": "11E9, FFFFE335, 320D",
        "81": "11CB, FFFFE329, 32B2",
        "82": "11A2, FFFFE320, 32F7",
        "83": "116D, FFFFE318, 32DC",
        "84": "113A, FFFFE30F, 3335",
        "85": "1109, FFFFE302, 3401",
        "86": "10CC, FFFFE2F6, 346D",
        "87": "1085, FFFFE2EC, 347A",
        "88": "1045, FFFFE2DA, 3563",
        "89": "FFB, FFFFE2C9, 35ED",
        "90": "FA6, FFFFE2B8, 3616",
        "91": "FB9, FFFFE22C, 36A4",
        "92": "1063, FFFFE0EA, 378E",
        "93": "1138, FFFFDF5A, 37A3",
        "94": "11EB, FFFFDDEE, 382A",
        "95": "1203, FFFFDD49, 38C3",
        "96": "11CC, FFFFDD47, 39AE",
        "97": "11A0, FFFFDD56, 39A4",
        "98": "1175, FFFFDD5F, 3A7B",
        "99": "110A, FFFFDD5E, 3B2D",
        "100": "1048, FFFFDD52, 3C44",
        "101": "F44, FFFFDD46, 3D36",
        "102": "E46, FFFFDD32, 3F07",
        "103": "D62, FFFFDD22, 3FDE",
        "104": "CE3, FFFFDD07, 412B",
        "105": "CA2, FFFFDCE8, 41C6",
        "106": "C6A, FFFFDCC7, 41E9",
        "107": "C4B, FFFFDC99, 42D4",
        "108": "C32, FFFFDC6C, 4348",
        "109": "C1D, FFFFDC40, 4346",
        "110": "C1E, FFFFDC0B, 440E",
        "111": "C1F, FFFFDBD9, 4461",
        "112": "C1F, FFFFDBAC, 443F",
        "113": "C30, FFFFDB7D, 446E",
        "114": "C51, FFFFDB4C, 44E4",
        "115": "C6C, FFFFDB27, 446D",
        "116": "C95, FFFFDAFF, 44BA",
        "117": "CB3, FFFFDAE3, 4499",
        "118": "CC3, FFFFDAD5, 4413",
        "119": "CCB, FFFFDACF, 4408"
      },
      "Scale": {},
      "Vector": {},
      "Vertex": {},
      "Normal": {},
      "Target": {},
      "Roll": {},
      "Angle": {},
      "Color": {},
      "Intensity": {},
      "Spot": {},
      "Point": {},
      "PositionName": null,
      "RotationName": "animation_00033404_mkey_44_rot_00030204",
      "ScaleName": null,
      "VectorName": null,
      "VertexName": null,
      "VertexItemName": null,
      "NormalItemName": null,
      "NormalName": null,
      "TargetName": null,
      "RollName": null,
      "AngleName": null,
      "ColorName": null,
      "IntensityName": null,
      "SpotName": null,
      "PointName": null
    },
    "51": {
      "Position": {},
      "Rotation": {
        "0": "63F, CF8, 12B1",
        "9": "659, D2D, 12B5",
        "12": "667, D4B, 12B5",
        "27": "676, D6E, 12B2",
        "28": "670, D62, 12B2",
        "29": "669, D53, 12B2",
        "30": "663, D42, 12B5",
        "31": "657, D2C, 12B2",
        "32": "64C, D13, 12B2",
        "33": "63F, CF8, 12B1",
        "34": "630, CD6, 12B2",
        "35": "617, CA5, 12AA",
        "36": "5F8, C6A, 12A1",
        "37": "5D5, C25, 1296",
        "38": "5A9, BD5, 1282",
        "39": "576, B7A, 1265",
        "40": "53D, B18, 1243",
        "41": "4FF, AAE, 1217",
        "42": "4BC, A3D, 11E2",
        "43": "475, 9C7, 11A3",
        "44": "42C, 94F, 115A",
        "45": "3E0, 8D5, 1103",
        "46": "397, 85D, 10A9",
        "47": "351, 7E9, 104F",
        "48": "312, 77B, FFB",
        "49": "2DA, 713, FB5",
        "50": "2A6, 6AF, F78",
        "51": "275, 64B, F3F",
        "52": "246, 5E9, F09",
        "53": "219, 588, ED7",
        "54": "1EF, 527, EAB",
        "55": "1C6, 4C9, E82",
        "56": "19E, 468, E63",
        "57": "178, 408, E49",
        "58": "153, 3A8, E35",
        "59": "12E, 344, E2A",
        "60": "108, 2DA, E2B",
        "61": "E1, 26D, E33",
        "62": "B7, 1F6, E45",
        "63": "8B, 17C, E5A",
        "64": "5B, F7, E73",
        "65": "2A, 72, E8A",
        "66": "17, 3E, ED3",
        "67": "3E, 9D, F71",
        "68": "97, 167, 1046",
        "69": "11D, 27D, 112D",
        "70": "1EB, 405, 122C",
        "71": "29D, 53D, 12EB",
        "72": "31F, 618, 135F",
        "73": "344, 656, 1381",
        "74": "32D, 62B, 1379",
        "75": "315, 5FE, 1370",
        "76": "2FB, 5D0, 1365",
        "77": "2E0, 5A0, 1359",
        "78": "2C7, 572, 134A",
        "79": "2AB, 540, 133A",
        "80": "291, 512, 1327",
        "81": "275, 4E0, 1312",
        "82": "25A, 4B1, 12FB",
        "83": "240, 485, 12E0",
        "84": "226, 458, 12C2",
        "85": "20B, 42A, 12A2",
        "86": "1F2, 401, 127E",
        "87": "1DC, 3DB, 1256",
        "88": "1C4, 3B4, 122B",
        "89": "1AE, 391, 11FC",
        "90": "19B, 373, 11C9",
        "91": "1B1, 3B6, 1177",
        "92": "1FF, 488, 10F4",
        "93": "25F, 5A0, 1052",
        "94": "2A9, 698, FB5",
        "95": "2BC, 6F4, F59",
        "96": "2AD, 6D5, F4B",
        "97": "2A4, 6B9, F53",
        "98": "298, 699, F57",
        "99": "286, 67A, F38",
        "100": "26A, 657, EE8",
        "101": "24A, 631, E7D",
        "102": "229, 60A, E12",
        "103": "213, 5F2, DBE",
        "104": "20A, 5E8, D9E",
        "105": "20E, 5EE, DA5",
        "106": "215, 5FD, DB3",
        "107": "21F, 60E, DC9",
        "108": "22C, 626, DE4",
        "109": "23B, 644, E03",
        "110": "24C, 661, E26",
        "111": "25E, 681, E49",
        "112": "271, 6A5, E6D",
        "113": "283, 6C4, E91",
        "114": "294, 6DF, EB8",
        "115": "2A5, 6FA, EDB",
        "116": "2B3, 70D, EFD",
        "117": "2BE, 71C, F17",
        "118": "2C6, 728, F27",
        "119": "2C8, 72C, F2E"
      },
      "Scale": {},
      "Vector": {},
      "Vertex": {},
      "Normal": {},
      "Target": {},
      "Roll": {},
      "Angle": {},
      "Color": {},
      "Intensity": {},
      "Spot": {},
      "Point": {},
      "PositionName": null,
      "RotationName": "animation_00033404_mkey_51_rot_00030954",
      "ScaleName": null,
      "VectorName": null,
      "VertexName": null,
      "VertexItemName": null,
      "NormalItemName": null,
      "NormalName": null,
      "TargetName": null,
      "RollName": null,
      "AngleName": null,
      "ColorName": null,
      "IntensityName": null,
      "SpotName": null,
      "PointName": null
    },
    "53": {
      "Position": {},
      "Rotation": {
        "0": "FFFFFE14, FFFFFC3F, 1355",
        "10": "FFFFFE35, FFFFFC84, 136A",
        "11": "FFFFFE3A, FFFFFC8F, 136A",
        "12": "FFFFFE3F, FFFFFC9A, 136F",
        "13": "FFFFFE45, FFFFFCA5, 1372",
        "14": "FFFFFE4A, FFFFFCAF, 1372",
        "27": "FFFFFE54, FFFFFCC3, 1376",
        "28": "FFFFFE4D, FFFFFCB5, 1373",
        "29": "FFFFFE45, FFFFFCA4, 136F",
        "30": "FFFFFE3B, FFFFFC90, 136D",
        "31": "FFFFFE30, FFFFFC79, 1364",
        "32": "FFFFFE22, FFFFFC5E, 135D",
        "33": "FFFFFE14, FFFFFC3F, 1355",
        "34": "FFFFFDFF, FFFFFC15, 134E",
        "35": "FFFFFDE4, FFFFFBDC, 1340",
        "36": "FFFFFDC1, FFFFFB93, 1332",
        "37": "FFFFFD97, FFFFFB3D, 1323",
        "38": "FFFFFD69, FFFFFADA, 130D",
        "39": "FFFFFD38, FFFFFA6D, 12EE",
        "40": "FFFFFD04, FFFFF9F6, 12CA",
        "41": "FFFFFCCF, FFFFF977, 129D",
        "42": "FFFFFC9C, FFFFF8F4, 1266",
        "43": "FFFFFC6B, FFFFF86E, 1223",
        "44": "FFFFFC3F, FFFFF7E8, 11D6",
        "45": "FFFFFC1D, FFFFF768, 1178",
        "46": "FFFFFC00, FFFFF6EC, 1114",
        "47": "FFFFFBEB, FFFFF679, 10AE",
        "48": "FFFFFBDC, FFFFF612, 104A",
        "49": "FFFFFBCF, FFFFF5B2, FF1",
        "50": "FFFFFBC4, FFFFF557, F9F",
        "51": "FFFFFBB8, FFFFF4F9, F50",
        "52": "FFFFFBAE, FFFFF49D, F03",
        "53": "FFFFFBA3, FFFFF440, EB9",
        "54": "FFFFFB98, FFFFF3DF, E73",
        "55": "FFFFFB8C, FFFFF37D, E30",
        "56": "FFFFFB7B, FFFFF312, DF7",
        "57": "FFFFFB69, FFFFF2A1, DC3",
        "58": "FFFFFB53, FFFFF22C, D94",
        "59": "FFFFFB37, FFFFF1A9, D70",
        "60": "FFFFFB11, FFFFF114, D59",
        "61": "FFFFFAE5, FFFFF075, D4B",
        "62": "FFFFFAAE, FFFFEFC0, D4A",
        "63": "FFFFFA73, FFFFEF04, D4D",
        "64": "FFFFFA31, FFFFEE35, D55",
        "65": "FFFFF9F0, FFFFED65, D5B",
        "66": "FFFFF9AD, FFFFECF3, D9D",
        "67": "FFFFF970, FFFFED31, E41",
        "68": "FFFFF942, FFFFEDF3, F23",
        "69": "FFFFF934, FFFFEF12, 101B",
        "70": "FFFFF958, FFFFF0C7, 1148",
        "71": "FFFFF990, FFFFF224, 1228",
        "72": "FFFFF9CA, FFFFF31B, 12B0",
        "73": "FFFFF9DD, FFFFF364, 12D5",
        "74": "FFFFF9CF, FFFFF339, 12C5",
        "75": "FFFFF9C2, FFFFF30E, 12B4",
        "76": "FFFFF9B6, FFFFF2E1, 12A0",
        "77": "FFFFF9A8, FFFFF2B2, 128A",
        "78": "FFFFF99F, FFFFF288, 1271",
        "79": "FFFFF995, FFFFF258, 1256",
        "80": "FFFFF98E, FFFFF22E, 1237",
        "81": "FFFFF987, FFFFF200, 1216",
        "82": "FFFFF983, FFFFF1D4, 11F2",
        "83": "FFFFF982, FFFFF1AC, 11CA",
        "84": "FFFFF982, FFFFF182, 119F",
        "85": "FFFFF983, FFFFF157, 1171",
        "86": "FFFFF987, FFFFF130, 113F",
        "87": "FFFFF990, FFFFF10E, 1109",
        "88": "FFFFF998, FFFFF0E8, 10D0",
        "89": "FFFFF9A5, FFFFF0C6, 1093",
        "90": "FFFFF9B6, FFFFF0A9, 1051",
        "91": "FFFFF9EE, FFFFF0E2, FFF",
        "92": "FFFFFA5E, FFFFF19A, F93",
        "93": "FFFFFAEA, FFFFF290, F10",
        "94": "FFFFFB65, FFFFF367, E8D",
        "95": "FFFFFB9E, FFFFF3B7, E36",
        "96": "FFFFFBA0, FFFFF3A2, E1C",
        "97": "FFFFFB9E, FFFFF399, E18",
        "98": "FFFFFB9B, FFFFF388, E0F",
        "99": "FFFFFBA2, FFFFF36F, DE2",
        "100": "FFFFFBB3, FFFFF341, D82",
        "101": "FFFFFBCC, FFFFF308, D04",
        "102": "FFFFFBE5, FFFFF2CC, C87",
        "103": "FFFFFBFD, FFFFF2A6, C24",
        "104": "FFFFFC08, FFFFF29B, BF9",
        "105": "FFFFFC0D, FFFFF2AC, BF9",
        "106": "FFFFFC13, FFFFF2CA, C01",
        "107": "FFFFFC15, FFFFF2E8, C13",
        "108": "FFFFFC19, FFFFF310, C2B",
        "109": "FFFFFC1D, FFFFF33F, C47",
        "110": "FFFFFC1F, FFFFF36B, C69",
        "111": "FFFFFC22, FFFFF39C, C8C",
        "112": "FFFFFC27, FFFFF3D0, CAE",
        "113": "FFFFFC29, FFFFF3FE, CD3",
        "114": "FFFFFC27, FFFFF423, CFB",
        "115": "FFFFFC27, FFFFF445, D20",
        "116": "FFFFFC23, FFFFF45C, D43",
        "117": "FFFFFC21, FFFFF46F, D5E",
        "118": "FFFFFC20, FFFFF47D, D70",
        "119": "FFFFFC1F, FFFFF480, D76"
      },
      "Scale": {},
      "Vector": {},
      "Vertex": {},
      "Normal": {},
      "Target": {},
      "Roll": {},
      "Angle": {},
      "Color": {},
      "Intensity": {},
      "Spot": {},
      "Point": {},
      "PositionName": null,
      "RotationName": "animation_00033404_mkey_53_rot_00030F54",
      "ScaleName": null,
      "VectorName": null,
      "VertexName": null,
      "VertexItemName": null,
      "NormalItemName": null,
      "NormalName": null,
      "TargetName": null,
      "RollName": null,
      "AngleName": null,
      "ColorName": null,
      "IntensityName": null,
      "SpotName": null,
      "PointName": null
    },
    "56": {
      "Position": {},
      "Rotation": {
        "0": "FFFFC612, 78E, 6D47",
        "1": "FFFFC60F, 7A1, 6DC9",
        "8": "FFFFC632, 78A, 6D75",
        "9": "FFFFC635, 79C, 6E01",
        "10": "FFFFC63C, 79C, 6E0C",
        "11": "FFFFC647, 788, 6D94",
        "12": "FFFFC64A, 79A, 6E21",
        "13": "FFFFC651, 799, 6E2B",
        "14": "FFFFC65C, 785, 6DB3",
        "17": "FFFFC66A, 796, 6E4F",
        "20": "FFFFC679, 781, 6DDD",
        "21": "FFFFC677, 794, 6E62",
        "23": "FFFFC677, 794, 6E62",
        "24": "FFFFC679, 781, 6DDD",
        "25": "FFFFC672, 795, 6E5A",
        "26": "FFFFC66C, 796, 6E52",
        "27": "FFFFC669, 783, 6DC6",
        "28": "FFFFC660, 784, 6DB8",
        "29": "FFFFC655, 786, 6DA8",
        "30": "FFFFC644, 79B, 6E17",
        "31": "FFFFC638, 789, 6D7E",
        "32": "FFFFC627, 78B, 6D64",
        "33": "FFFFC612, 78E, 6D46",
        "34": "FFFFC5F6, 7A2, 6D90",
        "35": "FFFFC5DD, 78E, 6CA8",
        "36": "FFFFC5BB, 788, 6C1B",
        "37": "FFFFC58F, 791, 6BF1",
        "38": "FFFFC561, 77F, 6B2C",
        "39": "FFFFC532, 74F, 69D5",
        "40": "FFFFC4FA, 726, 68F6",
        "41": "FFFFC4BD, 6EC, 6817",
        "42": "FFFFC47C, 69D, 6742",
        "43": "FFFFC437, 632, 667F",
        "44": "FFFFC3EB, 5BE, 6658",
        "45": "FFFFC3A5, 4FA, 655A",
        "46": "FFFFC354, 43C, 6589",
        "47": "FFFFC307, 34E, 6564",
        "48": "FFFFC2C0, 239, 64EA",
        "49": "FFFFC275, 138, 6514",
        "50": "FFFFC22B, 43, 6560",
        "51": "FFFFC1DF, FFFFFF97, 6647",
        "52": "FFFFC19B, FFFFFEE6, 66C7",
        "53": "FFFFC15C, FFFFFE74, 6759",
        "54": "FFFFC123, FFFFFE50, 67F8",
        "55": "FFFFC0FA, FFFFFE6E, 6821",
        "56": "FFFFC0D1, FFFFFF24, 694B",
        "57": "FFFFC0BE, 28, 69F8",
        "58": "FFFFC0C6, 164, 6A28",
        "59": "FFFFC0E3, 328, 6AD9",
        "60": "FFFFC134, 5E3, 6C5B",
        "61": "FFFFC209, 98E, 6D92",
        "62": "FFFFC3AF, DD4, 70B0",
        "63": "FFFFC6C7, 1219, 7402",
        "64": "FFFFCBE9, 15DE, 79D4",
        "65": "FFFFD351, 182D, 7FD4",
        "66": "FFFFDC35, 189F, 8667",
        "67": "FFFFE4F7, 1768, 8B4E",
        "68": "FFFFEC63, 1581, 8E15",
        "69": "FFFFF1E7, 13C2, 8D0D",
        "70": "FFFFF594, 129A, 8A2D",
        "71": "FFFFF769, 1201, 859D",
        "72": "FFFFF785, 11BE, 7ECB",
        "73": "FFFFFA38, 1304, 7EDB",
        "74": "FFFFFCE8, 1434, 7F38",
        "75": "223, 1540, 8463",
        "76": "8B7, 1503, 8B8C",
        "77": "E4F, 13EC, 90C0",
        "78": "1349, 123E, 93A7",
        "79": "17DB, 101C, 967E",
        "80": "1BC2, DF1, 9735",
        "81": "1F45, BC2, 9828",
        "82": "2237, 9E7, 97F8",
        "83": "2499, 88A, 96E2",
        "84": "2698, 7A3, 9624",
        "85": "2841, 733, 95E9",
        "86": "28FE, 724, 957B",
        "87": "28B5, 735, 94FA",
        "88": "281D, 748, 95C9",
        "89": "2760, 79C, 9651",
        "90": "26F1, 840, 9679",
        "91": "2757, 911, 9739",
        "92": "2865, A26, 9873",
        "93": "296E, BCB, 988B",
        "94": "2A43, D97, 991B",
        "95": "2A55, F31, 99B4",
        "96": "297E, 1084, 9AB6",
        "97": "27B4, 1219, 9A59",
        "98": "2587, 13A0, 9AB2",
        "99": "22FB, 1518, 9A58",
        "100": "208D, 160C, 9A50",
        "101": "1E32, 1698, 9A24",
        "102": "1BCE, 16FD, 9AED",
        "103": "191A, 1771, 9A80",
        "104": "166C, 17BC, 9B05",
        "105": "1381, 1812, 9AB3",
        "106": "106B, 1861, 9995",
        "107": "D61, 188C, 993E",
        "108": "A3E, 18A5, 980F",
        "109": "715, 18A3, 9615",
        "110": "3FD, 1877, 94BD",
        "111": "EB, 1827, 9292",
        "112": "FFFFFDB3, 17AC, 8F35",
        "113": "FFFFFA8F, 16E1, 8B80",
        "114": "FFFFF6AE, 1555, 8580",
        "115": "FFFFF6DD, 1512, 85BB",
        "116": "FFFFF753, 14E9, 86E9",
        "117": "FFFFF7CD, 14D4, 8774",
        "118": "FFFFF829, 14CC, 874E",
        "119": "FFFFF853, 14CB, 8770"
      },
      "Scale": {},
      "Vector": {},
      "Vertex": {},
      "Normal": {},
      "Target": {},
      "Roll": {},
      "Angle": {},
      "Color": {},
      "Intensity": {},
      "Spot": {},
      "Point": {},
      "PositionName": null,
      "RotationName": "animation_00033404_mkey_56_rot_00031584",
      "ScaleName": null,
      "VectorName": null,
      "VertexName": null,
      "VertexItemName": null,
      "NormalItemName": null,
      "NormalName": null,
      "TargetName": null,
      "RollName": null,
      "AngleName": null,
      "ColorName": null,
      "IntensityName": null,
      "SpotName": null,
      "PointName": null
    },
    "57": {
      "Position": {},
      "Rotation": {
        "0": "0, 0, FFFFE650",
        "1": "0, 0, FFFFE637",
        "8": "0, 0, FFFFE665",
        "9": "0, 0, FFFFE64F",
        "10": "0, 0, FFFFE654",
        "11": "0, 0, FFFFE672",
        "12": "0, 0, FFFFE65D",
        "13": "0, 0, FFFFE661",
        "14": "0, 0, FFFFE680",
        "16": "0, 0, FFFFE688",
        "17": "0, 0, FFFFE671",
        "19": "0, 0, FFFFE676",
        "20": "0, 0, FFFFE692",
        "21": "0, 0, FFFFE679",
        "23": "0, 0, FFFFE679",
        "24": "0, 0, FFFFE692",
        "25": "0, 0, FFFFE676",
        "26": "0, 0, FFFFE672",
        "27": "0, 0, FFFFE688",
        "30": "0, 0, FFFFE659",
        "31": "0, 0, FFFFE669",
        "32": "0, 0, FFFFE65E",
        "33": "0, 0, FFFFE650",
        "34": "0, 0, FFFFE623",
        "35": "0, 0, FFFFE620",
        "36": "0, 0, FFFFE5FC",
        "37": "0, 0, FFFFE5B9",
        "38": "0, 0, FFFFE58F",
        "39": "0, 0, FFFFE583",
        "40": "0, 0, FFFFE563",
        "41": "0, 0, FFFFE550",
        "42": "0, 0, FFFFE550",
        "43": "0, 0, FFFFE56B",
        "44": "0, 0, FFFFE589",
        "45": "0, 0, FFFFE60D",
        "46": "0, 0, FFFFE680",
        "47": "0, 0, FFFFE735",
        "48": "0, 0, FFFFE823",
        "49": "0, 0, FFFFE8FF",
        "50": "0, 0, FFFFE9DA",
        "51": "0, 0, FFFFEA6C",
        "52": "0, 0, FFFFEB1B",
        "53": "0, 0, FFFFEB9A",
        "54": "0, 0, FFFFEBD6",
        "55": "0, 0, FFFFEBE8",
        "56": "0, 0, FFFFEB5E",
        "57": "0, 0, FFFFEAA1",
        "58": "0, 0, FFFFE9CD",
        "59": "0, 0, FFFFE87E",
        "60": "0, 0, FFFFE68A",
        "61": "0, 0, FFFFE451",
        "62": "0, 0, FFFFE213",
        "63": "0, 0, FFFFE061",
        "64": "0, 0, FFFFDF59",
        "65": "0, 0, FFFFDF75",
        "66": "0, 0, FFFFE0A5",
        "67": "0, 0, FFFFE2F6",
        "68": "0, 0, FFFFE650",
        "69": "0, 0, FFFFEAC2",
        "70": "0, 0, FFFFF04F",
        "71": "0, 0, FFFFF742",
        "72": "0, 0, 0",
        "74": "0, 0, 0",
        "75": "0, 0, FFFFFA8E",
        "76": "0, 0, FFFFF37B",
        "77": "0, 0, FFFFEE76",
        "78": "0, 0, FFFFEA14",
        "79": "0, 0, FFFFE61A",
        "80": "0, 0, FFFFE2A8",
        "81": "0, 0, FFFFDF8B",
        "82": "0, 0, FFFFDCDC",
        "83": "0, 0, FFFFDAA7",
        "84": "0, 0, FFFFD8EF",
        "85": "0, 0, FFFFD7BF",
        "86": "0, 0, FFFFD749",
        "87": "0, 0, FFFFD76A",
        "88": "0, 0, FFFFD7BB",
        "89": "0, 0, FFFFD7F1",
        "90": "0, 0, FFFFD7AE",
        "91": "0, 0, FFFFD68F",
        "92": "0, 0, FFFFD4F6",
        "93": "0, 0, FFFFD3A4",
        "94": "0, 0, FFFFD2E9",
        "95": "0, 0, FFFFD31C",
        "96": "0, 0, FFFFD47D",
        "97": "0, 0, FFFFD704",
        "98": "0, 0, FFFFDA08",
        "99": "0, 0, FFFFDD00",
        "100": "0, 0, FFFFDF14",
        "101": "0, 0, FFFFE05E",
        "102": "0, 0, FFFFE196",
        "103": "0, 0, FFFFE2D9",
        "104": "0, 0, FFFFE409",
        "105": "0, 0, FFFFE566",
        "106": "0, 0, FFFFE6E1",
        "107": "0, 0, FFFFE878",
        "108": "0, 0, FFFFEA3C",
        "109": "0, 0, FFFFEC2B",
        "110": "0, 0, FFFFEE6B",
        "111": "0, 0, FFFFF0EE",
        "112": "0, 0, FFFFF418",
        "113": "0, 0, FFFFF840",
        "114": "0, 0, 0",
        "119": "0, 0, 0"
      },
      "Scale": {},
      "Vector": {},
      "Vertex": {},
      "Normal": {},
      "Target": {},
      "Roll": {},
      "Angle": {},
      "Color": {},
      "Intensity": {},
      "Spot": {},
      "Point": {},
      "PositionName": null,
      "RotationName": "animation_00033404_mkey_57_rot_00031C54",
      "ScaleName": null,
      "VectorName": null,
      "VertexName": null,
      "VertexItemName": null,
      "NormalItemName": null,
      "NormalName": null,
      "TargetName": null,
      "RollName": null,
      "AngleName": null,
      "ColorName": null,
      "IntensityName": null,
      "SpotName": null,
      "PointName": null
    },
    "58": {
      "Position": {},
      "Rotation": {
        "0": "0, 0, FFFFE735",
        "1": "0, 0, FFFFE719",
        "8": "0, 0, FFFFE74B",
        "9": "0, 0, FFFFE733",
        "10": "0, 0, FFFFE738",
        "11": "0, 0, FFFFE75A",
        "12": "0, 0, FFFFE742",
        "13": "0, 0, FFFFE747",
        "14": "0, 0, FFFFE769",
        "16": "0, 0, FFFFE771",
        "17": "0, 0, FFFFE759",
        "19": "0, 0, FFFFE75F",
        "20": "0, 0, FFFFE77D",
        "21": "0, 0, FFFFE762",
        "23": "0, 0, FFFFE762",
        "24": "0, 0, FFFFE77D",
        "25": "0, 0, FFFFE75E",
        "26": "0, 0, FFFFE75A",
        "27": "0, 0, FFFFE772",
        "30": "0, 0, FFFFE73E",
        "31": "0, 0, FFFFE750",
        "32": "0, 0, FFFFE743",
        "33": "0, 0, FFFFE735",
        "34": "0, 0, FFFFE703",
        "35": "0, 0, FFFFE700",
        "36": "0, 0, FFFFE6D8",
        "37": "0, 0, FFFFE68E",
        "38": "0, 0, FFFFE660",
        "39": "0, 0, FFFFE653",
        "40": "0, 0, FFFFE630",
        "41": "0, 0, FFFFE61B",
        "42": "0, 0, FFFFE61B",
        "43": "0, 0, FFFFE638",
        "44": "0, 0, FFFFE659",
        "45": "0, 0, FFFFE6EB",
        "46": "0, 0, FFFFE769",
        "47": "0, 0, FFFFE82F",
        "48": "0, 0, FFFFE935",
        "49": "0, 0, FFFFEA25",
        "50": "0, 0, FFFFEB13",
        "51": "0, 0, FFFFEBB7",
        "52": "0, 0, FFFFEC75",
        "53": "0, 0, FFFFECFD",
        "54": "0, 0, FFFFED3F",
        "55": "0, 0, FFFFED52",
        "56": "0, 0, FFFFECBD",
        "57": "0, 0, FFFFEBF1",
        "58": "0, 0, FFFFEB05",
        "59": "0, 0, FFFFE998",
        "60": "0, 0, FFFFE775",
        "61": "0, 0, FFFFE502",
        "62": "0, 0, FFFFE277",
        "63": "0, 0, FFFFE093",
        "64": "0, 0, FFFFDF6B",
        "65": "0, 0, FFFFDF8B",
        "66": "0, 0, FFFFE0DF",
        "67": "0, 0, FFFFE383",
        "68": "0, 0, FFFFE734",
        "69": "0, 0, FFFFEC14",
        "70": "0, 0, FFFFF20B",
        "71": "0, 0, FFFFF943",
        "72": "0, 0, 0",
        "74": "0, 0, 0",
        "75": "0, 0, FFFFFC74",
        "76": "0, 0, FFFFF565",
        "77": "0, 0, FFFFF012",
        "78": "0, 0, FFFFEB53",
        "79": "0, 0, FFFFE6FA",
        "80": "0, 0, FFFFE321",
        "81": "0, 0, FFFFDFA3",
        "82": "0, 0, FFFFDCA1",
        "83": "0, 0, FFFFDA25",
        "84": "0, 0, FFFFD836",
        "85": "0, 0, FFFFD6DF",
        "86": "0, 0, FFFFD65A",
        "87": "0, 0, FFFFD67F",
        "88": "0, 0, FFFFD6DB",
        "89": "0, 0, FFFFD718",
        "90": "0, 0, FFFFD6CC",
        "91": "0, 0, FFFFD589",
        "92": "0, 0, FFFFD3BC",
        "93": "0, 0, FFFFD227",
        "94": "0, 0, FFFFD154",
        "95": "0, 0, FFFFD18D",
        "96": "0, 0, FFFFD335",
        "97": "0, 0, FFFFD60C",
        "98": "0, 0, FFFFD972",
        "99": "0, 0, FFFFDCC9",
        "100": "0, 0, FFFFDF1E",
        "101": "0, 0, FFFFE090",
        "102": "0, 0, FFFFE1EC",
        "103": "0, 0, FFFFE357",
        "104": "0, 0, FFFFE4B2",
        "105": "0, 0, FFFFE634",
        "106": "0, 0, FFFFE7D4",
        "107": "0, 0, FFFFE992",
        "108": "0, 0, FFFFEB82",
        "109": "0, 0, FFFFED9A",
        "110": "0, 0, FFFFF005",
        "111": "0, 0, FFFFF2B5",
        "112": "0, 0, FFFFF609",
        "113": "0, 0, FFFFFA41",
        "114": "0, 0, 0",
        "119": "0, 0, 0"
      },
      "Scale": {},
      "Vector": {},
      "Vertex": {},
      "Normal": {},
      "Target": {},
      "Roll": {},
      "Angle": {},
      "Color": {},
      "Intensity": {},
      "Spot": {},
      "Point": {},
      "PositionName": null,
      "RotationName": "animation_00033404_mkey_58_rot_000322D4",
      "ScaleName": null,
      "VectorName": null,
      "VertexName": null,
      "VertexItemName": null,
      "NormalItemName": null,
      "NormalName": null,
      "TargetName": null,
      "RollName": null,
      "AngleName": null,
      "ColorName": null,
      "IntensityName": null,
      "SpotName": null,
      "PointName": null
    },
    "60": {
      "Position": {},
      "Rotation": {
        "0": "885, FFFF9073, 17A1",
        "1": "889, FFFF9084, 17C0",
        "8": "881, FFFF9063, 1789",
        "9": "885, FFFF9071, 17A3",
        "10": "884, FFFF906D, 179D",
        "11": "87F, FFFF9058, 1779",
        "12": "882, FFFF9066, 1792",
        "13": "881, FFFF9063, 178D",
        "14": "87C, FFFF904E, 1769",
        "16": "87A, FFFF9048, 175F",
        "17": "87E, FFFF9056, 177A",
        "19": "87D, FFFF9052, 1774",
        "20": "878, FFFF903F, 1753",
        "21": "87C, FFFF9050, 1770",
        "23": "87D, FFFF9050, 1770",
        "24": "878, FFFF9040, 1753",
        "25": "87D, FFFF9053, 1775",
        "26": "87E, FFFF9055, 1779",
        "27": "87A, FFFF9048, 175F",
        "30": "883, FFFF9069, 1797",
        "31": "880, FFFF9060, 1784",
        "32": "883, FFFF9069, 1792",
        "33": "885, FFFF9073, 17A1",
        "34": "877, FFFF9090, 17E5",
        "35": "839, FFFF908A, 180C",
        "36": "7DC, FFFF9093, 1871",
        "37": "764, FFFF90A9, 190E",
        "38": "6D0, FFFF90A7, 199C",
        "39": "623, FFFF908A, 1A10",
        "40": "56A, FFFF9072, 1AA6",
        "41": "4A6, FFFF904C, 1B31",
        "42": "3DD, FFFF9015, 1BA4",
        "43": "314, FFFF8FCC, 1BF3",
        "44": "252, FFFF8F7F, 1C38",
        "45": "195, FFFF8EFE, 1BEC",
        "46": "ED, FFFF8E89, 1BAB",
        "47": "57, FFFF8DFB, 1B04",
        "48": "FFFFFFDC, FFFF8D5B, 19FF",
        "49": "FFFFFF84, FFFF8CD0, 1902",
        "50": "FFFFFF51, FFFF8C52, 17F3",
        "51": "FFFFFF4C, FFFF8BF9, 1728",
        "52": "FFFFFF76, FFFF8BAC, 1626",
        "53": "FFFFFFD5, FFFF8B83, 154B",
        "54": "70, FFFF8B84, 14A7",
        "55": "14C, FFFF8BA5, 1417",
        "56": "279, FFFF8C1E, 142A",
        "57": "3F7, FFFF8CC4, 1451",
        "58": "5D2, FFFF8D9E, 1468",
        "59": "81F, FFFF8ED1, 14D7",
        "60": "B8E, FFFF9096, 1540",
        "61": "10D5, FFFF92C4, 1484",
        "62": "1858, FFFF9536, 1215",
        "63": "2233, FFFF96EC, CE3",
        "64": "2E40, FFFF971C, 4DF",
        "65": "3AC9, FFFF94B7, FFFFFAB9",
        "66": "461C, FFFF900A, FFFFEFCF",
        "67": "4F1C, FFFF8A44, FFFFE4B8",
        "68": "55F1, FFFF84E7, FFFFD967",
        "69": "5B1A, FFFF80FE, FFFFCD9A",
        "70": "5F6F, FFFF7EE7, FFFFC110",
        "71": "6371, FFFF7E97, FFFFB399",
        "72": "6769, FFFF7FD7, FFFFA68C",
        "73": "6BB4, FFFF8270, FFFFA221",
        "74": "7084, FFFF8630, FFFF9D83",
        "75": "75B9, FFFF8AE3, FFFF9D77",
        "76": "7B43, FFFF905C, FFFFA091",
        "77": "811C, FFFF9673, FFFFA170",
        "78": "876D, FFFF9CF3, FFFFA193",
        "79": "8E88, FFFFA3B4, FFFFA09C",
        "80": "9765, FFFFAA4F, FFFF9DC9",
        "81": "A41C, FFFFB057, FFFF96DF",
        "82": "B8D1, FFFFB483, FFFF87BE",
        "83": "D3FF, FFFFB502, FFFF71C1",
        "84": "E87A, FFFFB22F, FFFF61C6",
        "85": "F419, FFFFAE29, FFFF59CC",
        "86": "F8AD, FFFFAB90, FFFF5711",
        "87": "F895, FFFFAB79, FFFF5718",
        "88": "F678, FFFFACAD, FFFF5840",
        "89": "F378, FFFFADFC, FFFF5A97",
        "90": "F1E7, FFFFAE41, FFFF5CE3",
        "91": "F32D, FFFFADAF, FFFF5E85",
        "92": "F5D9, FFFFAD13, FFFF601F",
        "93": "F881, FFFFAC61, FFFF61EA",
        "94": "FA99, FFFFAB8B, FFFF6303",
        "95": "FB82, FFFFA99B, FFFF6310",
        "96": "FAB7, FFFFA7A3, FFFF61B2",
        "97": "F70E, FFFFA8BC, FFFF60D2",
        "98": "F036, FFFFAC51, FFFF61C0",
        "99": "E61A, FFFFAFB2, FFFF65FE",
        "100": "D7B0, FFFFB253, FFFF6FC7",
        "101": "C4BA, FFFFB350, FFFF7F3F",
        "102": "B182, FFFFB208, FFFF8EEA",
        "103": "A276, FFFFAECE, FFFF9A96",
        "104": "97B9, FFFFAA8D, FFFFA1FC",
        "105": "8FC4, FFFFA5CE, FFFFA6AE",
        "106": "897C, FFFFA0EC, FFFFA9DC",
        "107": "843E, FFFF9C1D, FFFFABEF",
        "108": "7FB5, FFFF9781, FFFFAD64",
        "109": "7BB2, FFFF9331, FFFFAE6E",
        "110": "7824, FFFF8F39, FFFFAEB3",
        "111": "74FD, FFFF8BAD, FFFFAE83",
        "112": "7239, FFFF8898, FFFFAD6E",
        "113": "7069, FFFF8657, FFFFAAB1",
        "114": "6FDE, FFFF8519, FFFFA4AF",
        "115": "7034, FFFF84A6, FFFFA572",
        "116": "7119, FFFF84B2, FFFFA5A8",
        "117": "7226, FFFF8509, FFFFA5AC",
        "118": "7301, FFFF856D, FFFFA5A4",
        "119": "735E, FFFF859B, FFFFA593"
      },
      "Scale": {},
      "Vector": {},
      "Vertex": {},
      "Normal": {},
      "Target": {},
      "Roll": {},
      "Angle": {},
      "Color": {},
      "Intensity": {},
      "Spot": {},
      "Point": {},
      "PositionName": null,
      "RotationName": "animation_00033404_mkey_60_rot_00032954",
      "ScaleName": null,
      "VectorName": null,
      "VertexName": null,
      "VertexItemName": null,
      "NormalItemName": null,
      "NormalName": null,
      "TargetName": null,
      "RollName": null,
      "AngleName": null,
      "ColorName": null,
      "IntensityName": null,
      "SpotName": null,
      "PointName": null
    }
  },
  "Frames": 120,
  "Name": "animation_00033404",
  "MdataName": "animation_00033404_mdat_00033024",
  "ModelParts": 62,
  "InterpolationMode": 0,
  "ShortRot": false
}